flask_maintenance.py
flask_maintenance/__init__.py
flask_maintenance/cli.py
Flask_Maintenance-0.0.1.dist-info/LICENSE
Flask_Maintenance-0.0.1.dist-info/METADATA
Flask_Maintenance-0.0.1.dist-info/WHEEL
Flask_Maintenance-0.0.1.dist-info/entry_points.txt
Flask_Maintenance-0.0.1.dist-info/top_level.txt
Flask_Maintenance-0.0.1.dist-info/RECORD
