Metadata-Version: 2.1
Name: Flask-Maintenance
Version: 0.0.1
Summary: Flask Extension to enable or disable Maintenance mode.
Home-page: https://github.com/akhilharihar/Flask-Maintenance
Author: Akhil Harihar
Author-email: hariharakhil@gmail.com
License: MIT
Platform: any
Classifier: Programming Language :: Python :: 3
Classifier: License :: OSI Approved :: MIT License
Classifier: Operating System :: OS Independent
Classifier: Framework :: Flask
Classifier: Intended Audience :: Developers
Classifier: Topic :: Software Development
Classifier: Development Status :: 2 - Pre-Alpha
Requires-Python: >=3.0
